<?xml version="1.0" encoding="UTF-8" standalone="yes"?>
<mensajes>
    <mensaje>
        <remitente>antoniodp07</remitente>
        <destinatario>silvia</destinatario>
        <mensaje>Hola</mensaje>
        <fecha>2025-10-13T12:07:00</fecha>
        <adjuntoTamano>0</adjuntoTamano>
    </mensaje>
    <mensaje>
        <remitente>antoniodp07</remitente>
        <destinatario>silvia</destinatario>
        <mensaje>h</mensaje>
        <fecha>2025-10-13T12:15:18</fecha>
        <adjuntoTamano>0</adjuntoTamano>
    </mensaje>
    <mensaje>
        <remitente>antoniodp07</remitente>
        <destinatario>silvia</destinatario>
        <mensaje>h</mensaje>
        <fecha>2025-10-13T12:15:19</fecha>
        <adjuntoTamano>0</adjuntoTamano>
    </mensaje>
    <mensaje>
        <remitente>antoniodp07</remitente>
        <destinatario>silvia</destinatario>
        <mensaje>h</mensaje>
        <fecha>2025-10-13T12:15:21</fecha>
        <adjuntoTamano>0</adjuntoTamano>
    </mensaje>
    <mensaje>
        <remitente>antoniodp07</remitente>
        <destinatario>silvia</destinatario>
        <mensaje>h</mensaje>
        <fecha>2025-10-13T12:15:22</fecha>
        <adjuntoTamano>0</adjuntoTamano>
    </mensaje>
    <mensaje>
        <remitente>antoniodp07</remitente>
        <destinatario>silvia</destinatario>
        <mensaje>h</mensaje>
        <fecha>2025-10-13T12:15:23</fecha>
        <adjuntoTamano>0</adjuntoTamano>
    </mensaje>
    <mensaje>
        <remitente>antoniodp07</remitente>
        <destinatario>silvia</destinatario>
        <mensaje>h</mensaje>
        <fecha>2025-10-13T12:15:24</fecha>
        <adjuntoTamano>0</adjuntoTamano>
    </mensaje>
    <mensaje>
        <remitente>antoniodp07</remitente>
        <destinatario>silvia</destinatario>
        <mensaje>h</mensaje>
        <fecha>2025-10-13T12:15:25</fecha>
        <adjuntoTamano>0</adjuntoTamano>
    </mensaje>
    <mensaje>
        <remitente>antoniodp07</remitente>
        <destinatario>silvia</destinatario>
        <mensaje>h</mensaje>
        <fecha>2025-10-13T12:15:30</fecha>
        <adjuntoTamano>0</adjuntoTamano>
    </mensaje>
    <mensaje>
        <remitente>antoniodp07</remitente>
        <destinatario>silvia</destinatario>
        <mensaje>h</mensaje>
        <fecha>2025-10-13T12:15:31</fecha>
        <adjuntoTamano>0</adjuntoTamano>
    </mensaje>
    <mensaje>
        <remitente>antoniodp07</remitente>
        <destinatario>silvia</destinatario>
        <mensaje>h</mensaje>
        <fecha>2025-10-13T12:15:33</fecha>
        <adjuntoTamano>0</adjuntoTamano>
    </mensaje>
    <mensaje>
        <remitente>antoniodp07</remitente>
        <destinatario>silvia</destinatario>
        <mensaje>hyhy</mensaje>
        <fecha>2025-10-13T12:15:35</fecha>
        <adjuntoTamano>0</adjuntoTamano>
    </mensaje>
    <mensaje>
        <remitente>silvia</remitente>
        <destinatario>antoniodp07</destinatario>
        <mensaje>Hola</mensaje>
        <fecha>2025-10-13T12:43:18</fecha>
        <adjuntoTamano>0</adjuntoTamano>
    </mensaje>
    <mensaje>
        <remitente>silvia</remitente>
        <destinatario>antoniodp07</destinatario>
        <mensaje>Como estas</mensaje>
        <fecha>2025-10-13T12:43:26</fecha>
        <adjuntoTamano>0</adjuntoTamano>
    </mensaje>
</mensajes>
